{
  "items": [
    {
      "type": "group",
      "ctime": 1693565175684,
      "items": [
        {
          "type": "file",
          "ctime": 1693562860341,
          "path": "1-Theory/5-OS-principle/Internal&design-principle/20-进程与线程.md",
          "subpath": "#**完整的进程切换步骤**",
          "title": "完整的进程切换步骤"
        },
        {
          "type": "file",
          "ctime": 1693565148772,
          "path": "1-Theory/5-OS-principle/Internal&design-principle/20-进程与线程.md",
          "subpath": "#^93a1bf",
          "title": "套管 jacketing"
        },
        {
          "type": "file",
          "ctime": 1693663468664,
          "path": "1-Theory/5-OS-principle/Internal&design-principle/30-并发.md",
          "subpath": "#资源分配拒绝(银行家算法)",
          "title": "银行家算法"
        },
        {
          "type": "file",
          "ctime": 1693663596445,
          "path": "1-Theory/5-OS-principle/Internal&design-principle/30-并发.md",
          "subpath": "#死锁检测算法(coffman 算法)",
          "title": "Coffman算法"
        },
        {
          "type": "file",
          "ctime": 1693985701846,
          "path": "1-Theory/5-OS-principle/Internal&design-principle/40-内存与虚存.md",
          "subpath": "#^55c770",
          "title": "基址寄存器、界限寄存器实现内存保护"
        },
        {
          "type": "file",
          "ctime": 1693986551100,
          "path": "1-Theory/5-OS-principle/Internal&design-principle/40-内存与虚存.md",
          "subpath": "#^18bf0a",
          "title": "抖动thrashing"
        },
        {
          "type": "file",
          "ctime": 1693986865631,
          "path": "1-Theory/5-OS-principle/Internal&design-principle/40-内存与虚存.md",
          "subpath": "#^6d9569",
          "title": "二级虚拟页表的计算方式"
        },
        {
          "type": "file",
          "ctime": 1693988404370,
          "path": "1-Theory/5-OS-principle/Internal&design-principle/40-内存与虚存.md",
          "subpath": "#置换策略",
          "title": "虚拟分页-置换策略"
        },
        {
          "type": "file",
          "ctime": 1693989041904,
          "path": "1-Theory/5-OS-principle/Internal&design-principle/40-内存与虚存.md",
          "subpath": "#工作集策略",
          "title": "工作集策略及PFF、VSWS"
        },
        {
          "type": "file",
          "ctime": 1694156253307,
          "path": "1-Theory/5-OS-principle/Internal&design-principle/50-CPU调度.md",
          "subpath": "#^a7452f",
          "title": "处理器抖动"
        },
        {
          "type": "file",
          "ctime": 1694156263515,
          "path": "1-Theory/5-OS-principle/Internal&design-principle/50-CPU调度.md",
          "subpath": "#^f60129",
          "title": "处理器碎片"
        },
        {
          "type": "file",
          "ctime": 1694158306205,
          "path": "1-Theory/5-OS-principle/Internal&design-principle/50-CPU调度.md",
          "subpath": "#最早 deadline 优先策略",
          "title": "最早ddl优先策略"
        },
        {
          "type": "file",
          "ctime": 1694158513562,
          "path": "1-Theory/5-OS-principle/Internal&design-principle/50-CPU调度.md",
          "subpath": "#^a93108",
          "title": "自愿空闲时间的最早ddl策略"
        },
        {
          "type": "file",
          "ctime": 1694244815185,
          "path": "1-Theory/5-OS-principle/Internal&design-principle/60-IO管理与磁盘.md",
          "subpath": "#DMA 工作流程",
          "title": "DMA工作流程"
        },
        {
          "type": "file",
          "ctime": 1694159199390,
          "path": "1-Theory/5-OS-principle/Internal&design-principle/50-CPU调度.md",
          "subpath": "#优先级反转",
          "title": "优先级反转"
        },
        {
          "type": "file",
          "ctime": 1694158548693,
          "path": "1-Theory/5-OS-principle/Internal&design-principle/50-CPU调度.md",
          "subpath": "#速率单调调度",
          "title": "速率单调调度"
        },
        {
          "type": "file",
          "ctime": 1694425936340,
          "path": "1-Theory/5-OS-principle/Internal&design-principle/40-内存与虚存.md",
          "subpath": "#^6b6500",
          "title": "静态重定位"
        },
        {
          "type": "file",
          "ctime": 1694430319599,
          "path": "1-Theory/5-OS-principle/Internal&design-principle/40-内存与虚存.md",
          "subpath": "#^e36fc3",
          "title": "Clock算法与Belady现象"
        },
        {
          "type": "file",
          "ctime": 1694425953443,
          "path": "1-Theory/5-OS-principle/Internal&design-principle/40-内存与虚存.md",
          "subpath": "#^f55749",
          "title": "动态重定位"
        },
        {
          "type": "file",
          "ctime": 1694502184288,
          "path": "1-Theory/5-OS-principle/Internal&design-principle/40-内存与虚存.md",
          "subpath": "#^668f31",
          "title": "抖动解决办法"
        },
        {
          "type": "file",
          "ctime": 1694502232867,
          "path": "1-Theory/5-OS-principle/Internal&design-principle/40-内存与虚存.md",
          "subpath": "#^c1a7bf",
          "title": "clock算法扫描速度快慢意味着什么？"
        }
      ],
      "title": "OS-principle"
    },
    {
      "type": "group",
      "ctime": 1693927604603,
      "items": [
        {
          "type": "file",
          "ctime": 1694350318696,
          "path": "1-Theory/2-DataStruct/dsa-cpp-deng/B-Vector+List/31-List-Exercise.md",
          "subpath": "#3-19 Josephus 环问题",
          "title": "Josephus problem"
        },
        {
          "type": "file",
          "ctime": 1694436283432,
          "path": "1-Theory/2-DataStruct/dsa-cpp-deng/C-Stack+Queue/40-Stack_Queue.md",
          "subpath": "#catalan 数应用",
          "title": "catalan(n)"
        },
        {
          "type": "file",
          "ctime": 1694519382981,
          "path": "1-Theory/2-DataStruct/dsa-cpp-deng/C-Stack+Queue/41-Stack-queue-Exercise.md",
          "subpath": "#4-11 中缀表达式运算中栈内括号数问题",
          "title": "中缀表达式运算中括号数问题"
        },
        {
          "type": "file",
          "ctime": 1694776343320,
          "path": "1-Theory/2-DataStruct/dsa-cpp-deng/D-Tree+BST+BBST/50-Tree.md",
          "subpath": "#^b26f71",
          "title": "二叉树度数、节点数、边数的关系"
        },
        {
          "type": "file",
          "ctime": 1695034666607,
          "path": "1-Theory/2-DataStruct/dsa-cpp-deng/D-Tree+BST+BBST/51-Tree-Exercise.md",
          "subpath": "#5-16 分析 travIn_I3 的时间复杂度",
          "title": "分析travIn_I3的时间复杂度"
        },
        {
          "type": "file",
          "ctime": 1695037210155,
          "path": "1-Theory/2-DataStruct/dsa-cpp-deng/D-Tree+BST+BBST/51-Tree-Exercise.md",
          "subpath": "#5-30 键树 Trie",
          "title": "Trie键树"
        },
        {
          "type": "group",
          "ctime": 1697701223496,
          "items": [
            {
              "type": "file",
              "ctime": 1697701292826,
              "path": "1-Theory/2-DataStruct/dsa-cpp-deng/A-Introduction/10-Introduction.md",
              "subpath": "#迭代与递归应用：总和最大区段",
              "title": "总和最大区段问题"
            },
            {
              "type": "file",
              "ctime": 1697701329746,
              "path": "1-Theory/2-DataStruct/dsa-cpp-deng/A-Introduction/10-Introduction.md",
              "subpath": "#求 fib(n)",
              "title": "动态规划求Fibonacci序列"
            },
            {
              "type": "file",
              "ctime": 1697701380476,
              "path": "1-Theory/2-DataStruct/dsa-cpp-deng/A-Introduction/10-Introduction.md",
              "subpath": "#最长公共子序列",
              "title": "最长公共子序列LCS问题"
            },
            {
              "type": "file",
              "ctime": 1697701468614,
              "path": "1-Theory/2-DataStruct/dsa-cpp-deng/A-Introduction/10-Introduction.md",
              "subpath": "#局限 1 缓存——就地循环位移",
              "title": "向量元素就地循环位移问题"
            },
            {
              "type": "file",
              "ctime": 1697701524391,
              "path": "1-Theory/2-DataStruct/dsa-cpp-deng/A-Introduction/10-Introduction.md",
              "subpath": "#从 O (n)到 O (r=logn)",
              "title": "快速幂计算问题"
            },
            {
              "type": "file",
              "ctime": 1697701575776,
              "path": "1-Theory/2-DataStruct/dsa-cpp-deng/A-Introduction/10-Introduction.md",
              "subpath": "#局限 3 随机数",
              "title": "(伪)随机数生成问题"
            },
            {
              "type": "file",
              "ctime": 1697701683907,
              "path": "1-Theory/2-DataStruct/dsa-cpp-deng/A-Introduction/11-Intro-Exercise.md",
              "subpath": "#1-12 countOnes 算法改进",
              "title": "快速计算整数二进制表示的1位数"
            },
            {
              "type": "file",
              "ctime": 1697702141471,
              "path": "1-Theory/2-DataStruct/dsa-cpp-deng/A-Introduction/11-Intro-Exercise.md",
              "subpath": "#更相减损术",
              "title": "更相减损术"
            },
            {
              "type": "file",
              "ctime": 1697778997653,
              "path": "1-Theory/2-DataStruct/dsa-cpp-deng/A-Introduction/12-Instances-of-recursion.md",
              "subpath": "#Hanoi 问题",
              "title": "Hanoi问题"
            },
            {
              "type": "file",
              "ctime": 1697781942744,
              "path": "1-Theory/2-DataStruct/dsa-cpp-deng/C-Stack+Queue/43-Probing-backtracking.md",
              "subpath": "#八皇后问题",
              "title": "八皇后问题"
            },
            {
              "type": "file",
              "ctime": 1697781955896,
              "path": "1-Theory/2-DataStruct/dsa-cpp-deng/C-Stack+Queue/43-Probing-backtracking.md",
              "subpath": "#迷宫寻径",
              "title": "迷宫寻径问题"
            }
          ],
          "title": "算法问题"
        },
        {
          "type": "group",
          "ctime": 1697701980171,
          "items": [
            {
              "type": "file",
              "ctime": 1697701915906,
              "path": "1-Theory/2-DataStruct/dsa-cpp-deng/A-Introduction/11-Intro-Exercise.md",
              "subpath": "#fib (k)的递归实例在执行中出现了多少次？",
              "title": "fib(k)二分递归实例出现次数问题"
            },
            {
              "type": "file",
              "ctime": 1697702320092,
              "path": "1-Theory/2-DataStruct/dsa-cpp-deng/A-Introduction/11-Intro-Exercise.md",
              "subpath": "#O (√n）",
              "title": "O(√n)的形式"
            },
            {
              "type": "file",
              "ctime": 1697702554793,
              "path": "1-Theory/2-DataStruct/dsa-cpp-deng/A-Introduction/11-Intro-Exercise.md",
              "subpath": "#递归与调用 1",
              "title": "递归调用：线性递归实例分析"
            },
            {
              "type": "file",
              "ctime": 1697702681452,
              "path": "1-Theory/2-DataStruct/dsa-cpp-deng/A-Introduction/11-Intro-Exercise.md",
              "subpath": "#递归与调用 4",
              "title": "递归调用：二分递归实例分析"
            },
            {
              "type": "file",
              "ctime": 1697785086634,
              "path": "1-Theory/2-DataStruct/dsa-cpp-deng/B-Vector+List/20-Vector.md",
              "subpath": "#平均分析 Vs. 分摊分析",
              "title": "平均分析 Vs. 分摊分析"
            },
            {
              "type": "file",
              "ctime": 1697785398564,
              "path": "1-Theory/2-DataStruct/dsa-cpp-deng/B-Vector+List/20-Vector.md",
              "subpath": "#二分查找 b",
              "title": "二分查找B和C的特点"
            },
            {
              "type": "file",
              "ctime": 1697785676488,
              "path": "1-Theory/2-DataStruct/dsa-cpp-deng/B-Vector+List/20-Vector.md",
              "subpath": "#2-way merge",
              "title": "二路归并排序的复杂度、优缺点与改进"
            },
            {
              "type": "file",
              "ctime": 1697866859992,
              "path": "1-Theory/2-DataStruct/dsa-cpp-deng/B-Vector+List/21-Vector-Exercise.md",
              "subpath": "#2-18 binSearch 查找长度分析",
              "title": "二分搜索的平均查找长度"
            },
            {
              "type": "file",
              "ctime": 1697866943951,
              "path": "1-Theory/2-DataStruct/dsa-cpp-deng/B-Vector+List/21-Vector-Exercise.md",
              "subpath": "#2-20 对比 binSearch-A 与 fibSearch",
              "title": "二分查找A与Fib查找对比"
            },
            {
              "type": "file",
              "ctime": 1697867412297,
              "path": "1-Theory/2-DataStruct/dsa-cpp-deng/B-Vector+List/21-Vector-Exercise.md",
              "subpath": "#2-24-c 插值查找搜索区间与复杂度分析",
              "title": "插值查找: 查找区间宽度缩减速度和整体复杂度"
            },
            {
              "type": "file",
              "ctime": 1697867736802,
              "path": "1-Theory/2-DataStruct/dsa-cpp-deng/B-Vector+List/21-Vector-Exercise.md",
              "subpath": "#2-27 改进 mergeSort ()适应于大致有序情况",
              "title": "大致有序情况时归并排序的改进策略"
            },
            {
              "type": "file",
              "ctime": 1697868459569,
              "path": "1-Theory/2-DataStruct/dsa-cpp-deng/B-Vector+List/21-Vector-Exercise.md",
              "subpath": "#2-41 基数排序思想",
              "title": "基数排序的思想基础"
            },
            {
              "type": "file",
              "ctime": 1697875023215,
              "path": "1-Theory/2-DataStruct/dsa-cpp-deng/B-Vector+List/30-List.md",
              "subpath": "#循环节",
              "title": "循环节"
            }
          ],
          "title": "知识点细节"
        },
        {
          "type": "group",
          "ctime": 1697703064545,
          "items": [
            {
              "type": "file",
              "ctime": 1697703072225,
              "path": "1-Theory/2-DataStruct/dsa-cpp-deng/A-Introduction/16-Stirling-Approximation.md",
              "subpath": "#Intro",
              "title": "Stirling渐进"
            },
            {
              "type": "file",
              "ctime": 1697703106362,
              "path": "1-Theory/2-DataStruct/dsa-cpp-deng/A-Introduction/15-Little-o-notation.md",
              "title": "Little-o-notation"
            },
            {
              "type": "file",
              "ctime": 1697703136858,
              "path": "1-Theory/2-DataStruct/dsa-cpp-deng/A-Introduction/14-Lowerbound-analyze.md",
              "subpath": "#线性规约",
              "title": "线性规约Linear reduction"
            },
            {
              "type": "file",
              "ctime": 1697703177173,
              "path": "1-Theory/2-DataStruct/dsa-cpp-deng/A-Introduction/14-Lowerbound-analyze.md",
              "subpath": "#CBA排序算法下界",
              "title": "CBA排序算法下界分析(比较树)"
            },
            {
              "type": "file",
              "ctime": 1697784909206,
              "path": "1-Theory/2-DataStruct/dsa-cpp-deng/A-Introduction/13-Dynamic-Programming.md",
              "title": "动态规划"
            },
            {
              "type": "file",
              "ctime": 1697866313856,
              "path": "1-Theory/2-DataStruct/dsa-cpp-deng/B-Vector+List/21-Vector-Exercise.md",
              "subpath": "#2-6 permute 生成随机排列",
              "title": "Fisher 随机数生成算法与分析"
            },
            {
              "type": "file",
              "ctime": 1697866597733,
              "path": "1-Theory/2-DataStruct/dsa-cpp-deng/B-Vector+List/21-Vector-Exercise.md",
              "subpath": "#2-12-d deduplicate ()可以改进到什么地步？",
              "title": "无序向量唯一化的时间下界"
            },
            {
              "type": "file",
              "ctime": 1694013820245,
              "path": "1-Theory/2-DataStruct/dsa-cpp-deng/B-Vector+List/21-Vector-Exercise.md",
              "subpath": "#2-21 指数查找 expSearch",
              "title": "指数查找"
            },
            {
              "type": "file",
              "ctime": 1697867052780,
              "path": "1-Theory/2-DataStruct/dsa-cpp-deng/B-Vector+List/21-Vector-Exercise.md",
              "subpath": "#2-22 马鞍查找——二维向量查找",
              "title": "马鞍查找"
            },
            {
              "type": "file",
              "ctime": 1697867457235,
              "path": "1-Theory/2-DataStruct/dsa-cpp-deng/B-Vector+List/21-Vector-Exercise.md",
              "subpath": "#2-23 判断分支深入的代价严重不对称的查找",
              "title": "鸡蛋查找：分支深入代价严重不对称"
            },
            {
              "type": "file",
              "ctime": 1697868571905,
              "path": "1-Theory/2-DataStruct/dsa-cpp-deng/B-Vector+List/24-Bitmap.md",
              "title": "Bitmap"
            },
            {
              "type": "file",
              "ctime": 1697870106803,
              "path": "1-Theory/2-DataStruct/dsa-cpp-deng/B-Vector+List/22-In-place-mergeSort.md",
              "title": "In-place mergesort"
            },
            {
              "type": "file",
              "ctime": 1697870122531,
              "path": "1-Theory/2-DataStruct/dsa-cpp-deng/B-Vector+List/23-N-way-merge.md",
              "title": "N-way merge"
            }
          ],
          "title": "拓展延伸"
        },
        {
          "type": "group",
          "ctime": 1697865861190,
          "items": [
            {
              "type": "file",
              "ctime": 1697865876536,
              "path": "1-Theory/2-DataStruct/dsa-cpp-deng/B-Vector+List/21-Vector-Exercise.md",
              "subpath": "#2-5 分摊分析——二进制整数递增",
              "title": "分摊分析实例：二进制整数递增"
            },
            {
              "type": "file",
              "ctime": 1697866739521,
              "path": "1-Theory/2-DataStruct/dsa-cpp-deng/B-Vector+List/21-Vector-Exercise.md",
              "subpath": "#2-15 CBA 算法下界分析",
              "title": "比较树高度分析: CBA排序"
            },
            {
              "type": "file",
              "ctime": 1697868071618,
              "path": "1-Theory/2-DataStruct/dsa-cpp-deng/B-Vector+List/21-Vector-Exercise.md",
              "subpath": "#2-39 CBA 插入两元素到有序序列的比较次数分析",
              "title": "插入多个元素到有序序列的比较次数"
            },
            {
              "type": "file",
              "ctime": 1697868166055,
              "path": "1-Theory/2-DataStruct/dsa-cpp-deng/B-Vector+List/21-Vector-Exercise.md",
              "subpath": "#2-40 CBA 找出最大者、次大者",
              "title": "找出向量中最大者、次大者的策略优化"
            }
          ],
          "title": "习题解析好题"
        }
      ],
      "title": "DSA-cpp-deng"
    },
    {
      "type": "group",
      "ctime": 1694869807484,
      "items": [
        {
          "type": "file",
          "ctime": 1694869858991,
          "path": "1-Theory/5-OS-principle/rCore-tutorial/0-OS-overview/30-OS-abstraction.md",
          "subpath": "#普通控制流",
          "title": "Common Control Flow"
        },
        {
          "type": "file",
          "ctime": 1694870055231,
          "path": "1-Theory/5-OS-principle/rCore-tutorial/0-OS-overview/30-OS-abstraction.md",
          "subpath": "#异常控制流",
          "title": "Exceptional Control Flow"
        },
        {
          "type": "file",
          "ctime": 1695109259318,
          "path": "1-Theory/5-OS-principle/rCore-tutorial/1-App-basic-exec-env/30-Qemu-boot-and-compile-process.md",
          "subpath": "#^662cbb",
          "title": "真实计算机的加电启动过程"
        },
        {
          "type": "file",
          "ctime": 1695111035079,
          "path": "1-Theory/5-OS-principle/rCore-tutorial/1-App-basic-exec-env/30-Qemu-boot-and-compile-process.md",
          "subpath": "#编译流程",
          "title": "编译流程"
        },
        {
          "type": "file",
          "ctime": 1695119674413,
          "path": "1-Theory/5-OS-principle/rCore-tutorial/1-App-basic-exec-env/50-Support-func-call-for-kernel.md",
          "subpath": "#^8eaaaf",
          "title": "riscv中如何实现函数调用返回？"
        },
        {
          "type": "group",
          "ctime": 1695533698795,
          "items": [
            {
              "type": "file",
              "ctime": 1695533637471,
              "path": "1-Theory/5-OS-principle/rCore-tutorial/3-Multiprog-and-time-sharing/40-Time-sharing-preemptive.md",
              "subpath": "#^9359cd",
              "title": "第三章新增syscall-sys_get_time"
            },
            {
              "type": "file",
              "ctime": 1696323258560,
              "path": "1-Theory/5-OS-principle/rCore-tutorial/6-File-system/10-Interface.md",
              "subpath": "#文件打开",
              "title": "sys_open"
            }
          ],
          "title": "syscall"
        },
        {
          "type": "file",
          "ctime": 1695634564666,
          "path": "1-Theory/5-OS-principle/rCore-tutorial/4-Memory-address/40-Manage-SV39-multilevel-pagetable.md",
          "subpath": "#^4e745d",
          "title": "多级页表的恒等映射"
        },
        {
          "type": "group",
          "ctime": 1695895111494,
          "items": [
            {
              "type": "file",
              "ctime": 1696258321098,
              "path": "1-Theory/5-OS-principle/rCore-tutorial/5-Process/40-Scheduling.md",
              "subpath": "#^b901a9",
              "title": "Stride调度"
            },
            {
              "type": "file",
              "ctime": 1696257570879,
              "path": "1-Theory/5-OS-principle/rCore-tutorial/5-Process/40-Scheduling.md",
              "subpath": "#^439fb0",
              "title": "Lottery调度"
            },
            {
              "type": "file",
              "ctime": 1695895133383,
              "path": "1-Theory/5-OS-principle/rCore-tutorial/5-Process/10-Concepts-and-syscall.md",
              "subpath": "#^87a5b4",
              "title": "僵尸进程"
            },
            {
              "type": "file",
              "ctime": 1697711502036,
              "path": "1-Theory/5-OS-principle/rCore-tutorial/Practice/2-批处理操作系统.md",
              "subpath": "#^5fa656",
              "title": "地址空间布局随机化ASLR"
            }
          ],
          "title": "琐碎概念"
        },
        {
          "type": "group",
          "ctime": 1697711353246,
          "items": [
            {
              "type": "file",
              "ctime": 1697711368801,
              "path": "1-Theory/5-OS-principle/rCore-tutorial/Practice/2-批处理操作系统.md",
              "subpath": "#函数调用与系统调用区别",
              "title": "函数调用与系统调用区别"
            },
            {
              "type": "file",
              "ctime": 1697711452787,
              "path": "1-Theory/5-OS-principle/rCore-tutorial/Practice/2-批处理操作系统.md",
              "subpath": "#用户程序库形式的 OS 被破坏的方式",
              "title": "用户程序库形式的 OS 被破坏的方式"
            },
            {
              "type": "file",
              "ctime": 1697711488355,
              "path": "1-Theory/5-OS-principle/rCore-tutorial/Practice/2-批处理操作系统.md",
              "subpath": "#编译器/CPU/OS 合作避免破坏",
              "title": "编译器/CPU/OS 合作避免破坏"
            },
            {
              "type": "file",
              "ctime": 1697711623526,
              "path": "1-Theory/5-OS-principle/rCore-tutorial/Practice/2-批处理操作系统.md",
              "subpath": "#Trap 上下文的理解",
              "title": "Trap 上下文的理解"
            },
            {
              "type": "file",
              "ctime": 1697787508806,
              "path": "1-Theory/5-OS-principle/rCore-tutorial/Practice/3-多道程序与分时多任务.md",
              "subpath": "#任务地址空间中的数据和代码段类型",
              "title": "任务地址空间中的数据和代码段类型"
            },
            {
              "type": "file",
              "ctime": 1697787611865,
              "path": "1-Theory/5-OS-principle/rCore-tutorial/Practice/3-多道程序与分时多任务.md",
              "subpath": "#特权级上下文和任务上下文的异同",
              "title": "特权级上下文和任务上下文的异同"
            },
            {
              "type": "file",
              "ctime": 1697787767741,
              "path": "1-Theory/5-OS-principle/rCore-tutorial/Practice/3-多道程序与分时多任务.md",
              "subpath": "#上下文切换需要使用汇编语言实现的原因",
              "title": "上下文切换需要使用汇编语言实现的原因"
            }
          ],
          "title": "简答题"
        },
        {
          "type": "group",
          "ctime": 1697711530985,
          "items": [
            {
              "type": "file",
              "ctime": 1697711388024,
              "path": "1-Theory/5-OS-principle/rCore-tutorial/Practice/2-批处理操作系统.md",
              "subpath": "#异常/中断的委托",
              "title": "RISC-V异常/中断的委托"
            },
            {
              "type": "file",
              "ctime": 1697711550149,
              "path": "1-Theory/5-OS-principle/rCore-tutorial/Practice/2-批处理操作系统.md",
              "subpath": "#RISC-V 的 S 态特权指令介绍",
              "title": "RISC-V 的 S 态特权指令介绍"
            },
            {
              "type": "file",
              "ctime": 1697711575901,
              "path": "1-Theory/5-OS-principle/rCore-tutorial/Practice/2-批处理操作系统.md",
              "subpath": "#RISC-V 的 trap 硬件操作",
              "title": "RISC-V 的 trap 硬件操作"
            },
            {
              "type": "file",
              "ctime": 1697711597454,
              "path": "1-Theory/5-OS-principle/rCore-tutorial/Practice/2-批处理操作系统.md",
              "subpath": "#RISC-V 支持的中断/异常及细节",
              "title": "RISC-V 支持的中断/异常及细节"
            },
            {
              "type": "file",
              "ctime": 1697787148044,
              "path": "1-Theory/5-OS-principle/rCore-tutorial/Practice/3-多道程序与分时多任务.md",
              "subpath": "#如何判断进入 OS 内核的起因是调用还是异常？",
              "title": "判断进入 OS 内核的起因是调用还是异常"
            },
            {
              "type": "file",
              "ctime": 1697787213653,
              "path": "1-Theory/5-OS-principle/rCore-tutorial/Practice/3-多道程序与分时多任务.md",
              "subpath": "#中断机制中 PLIC 和 CLINT",
              "title": "中断机制中 PLIC 和 CLINT 的作用"
            },
            {
              "type": "file",
              "ctime": 1697787270056,
              "path": "1-Theory/5-OS-principle/rCore-tutorial/Practice/3-多道程序与分时多任务.md",
              "subpath": "#RISC-V 中断嵌套",
              "title": "RISC-V 中断嵌套"
            },
            {
              "type": "file",
              "ctime": 1697787852695,
              "path": "1-Theory/5-OS-principle/rCore-tutorial/Practice/3-多道程序与分时多任务.md",
              "subpath": "#Linux 与 RISC-V",
              "title": "Linux与RISC-V"
            }
          ],
          "title": "RISC-V相关"
        }
      ],
      "title": "rCore-tips"
    }
  ]
}